MANIFEST.in
README.md
setup.py
SaossionPage/__init__.py
SaossionPage.egg-info/PKG-INFO
SaossionPage.egg-info/SOURCES.txt
SaossionPage.egg-info/dependency_links.txt
SaossionPage.egg-info/requires.txt
SaossionPage.egg-info/top_level.txt
SaossionPage/main/Config.py
SaossionPage/main/Listen_Console.py
SaossionPage/main/Listen_Ws.py
SaossionPage/main/Listen_tree.py
SaossionPage/main/SaoMouse.py
SaossionPage/main/SaossionPage.py
SaossionPage/main/Tool.py
SaossionPage/main/code_frame.py
SaossionPage/main/__pycache__/Config.cpython-311.pyc
SaossionPage/main/__pycache__/Listen_Ws.cpython-311.pyc
SaossionPage/main/__pycache__/SaossionPage.cpython-311.pyc
SaossionPage/main/js/Tool.js
SaossionPage/main/js/html2canvas.min.js
SaossionPage/main/js/takeScreenshot.js