Metadata-Version: 2.1
Name: SaossionPage
Version: 1.0.7
Summary: A sao shen library
Author: sao shen
Author-email: 
Keywords: python,menu,saoshen,windows,SaossionPage,linux
Classifier: Development Status :: 1 - Planning
Classifier: Intended Audience :: Developers
Classifier: Programming Language :: Python :: 3
Classifier: Operating System :: Unix
Classifier: Operating System :: MacOS :: MacOS X
Classifier: Operating System :: Microsoft :: Windows
